PyDictXML/PyDictXML.py
PyDictXML/__init__.py
PyDictXML-1.0.1.dist-info/LICENSE
PyDictXML-1.0.1.dist-info/METADATA
PyDictXML-1.0.1.dist-info/WHEEL
PyDictXML-1.0.1.dist-info/entry_points.txt
PyDictXML-1.0.1.dist-info/top_level.txt
PyDictXML-1.0.1.dist-info/RECORD
