Metadata-Version: 2.1
Name: PyDictXML
Version: 1.0.1
Summary: PyDictXML is a high-performance Python library designed to seamlessly replace dicttoxml, offering users an improved experience in XML string generation. With PyDictXML, users can effortlessly transition from dicttoxml without any code-level changes, benefiting from enhanced performance and efficiency.
Home-page: https://github.com/KumudithaBandara/PyDictXML
Author: Kumuditha Bandara
Author-email: Kumuditha Bandara <kumu.bandara.kb97@gmail.com>
License: GPLv2
Project-URL: homepage, https://github.com/KumudithaBandara/PyDictXML
Classifier: Programming Language :: Python :: 3
Classifier: Programming Language :: Python :: 3.10
Classifier: License :: OSI Approved :: GNU General Public License v2 (GPLv2)
Classifier: Operating System :: OS Independent
Requires-Python: >=3.10
License-File: LICENSE
